{
  "id": "github-light",
  "name": "GitHub Light",
  "appearance": "light",
  "cssVars": {
    "--bg-0": "#ffffff",
    "--bg-1": "#f6f8fa",
    "--bg-2": "#eaeef2",
    "--bg-3": "#d0d7de",
    "--fg-0": "#1f2328",
    "--fg-1": "#424a53",
    "--fg-2": "#656d76",
    "--fg-3": "#8c959f",
    "--border": "#d0d7de",
    "--border-bright": "#8c959f",
    "--focus": "#0969da",
    "--focus-glow": "rgba(9, 105, 218, 0.18)",
    "--accent-green": "#1a7f37",
    "--accent-amber": "#9a6700",
    "--accent-red": "#cf222e",
    "--accent-cyan": "#0969da",
    "--accent-magenta": "#8250df",
    "--accent-blue": "#0969da",
    "--workspace-neutral": "#8c959f",
    "--workspace-red": "#cf222e",
    "--workspace-orange": "#bc4c00",
    "--workspace-green": "#1a7f37",
    "--workspace-yellow": "#9a6700",
    "--workspace-cyan": "#0969da",
    "--workspace-blue": "#0969da",
    "--workspace-purple": "#8250df",
    "--window-opacity-bg": "rgba(255, 255, 255, 0.92)"
  },
  "ansi": [
    "#24292f",
    "#cf222e",
    "#116329",
    "#4d2d00",
    "#0969da",
    "#8250df",
    "#0969da",
    "#6e7781",
    "#57606a",
    "#a40e26",
    "#116329",
    "#633c01",
    "#0550ae",
    "#8250df",
    "#0969da",
    "#1f2328"
  ],
  "cursor": "#1f2328",
  "cursorText": "#ffffff",
  "selection": "rgba(9, 105, 218, 0.2)"
}
